<?xml version="1.0" encoding="UTF-8"?>

<!-- Design space definition file for VAD example (considering connection with A-DSE and MOST) -->

<design_space xmlns="http://www.multicube.eu/" version="1.4">
	<simulator> 
		<simulator_executable path="kista-xml" />
	</simulator>
	
	<parameters>
		
		<!-- Processing resources -->
		<!--
		<parameter name="PE_NODES" description ="" type="string" min="1" max="2"/>
			-->	
			<!-- Mapping -->
<!--			
		<parameter name="T1_MAP" description ="Mapping of the first task" type="integer" min="1" max="2"/>

		<parameter name="T2_MAP" description ="Mapping of the second task" type="string">
			<item value="PE1" />
			<item value="PE2" />
		</parameter>

		<parameter name="T3_MAP" description ="Mapping of the third task" type="string">
			<item value="PE1" />
			<item value="PE2" />
		</parameter>
		
		<parameter name="PE_FREQ_1" description ="Frequency of the first processor" type="string">
			<item value="50" />
			<item value="100" />			
		</parameter>
-->
				<!-- Communication resources -->
<!--				
		<parameter name="SLOTS_PE0" description ="Number of TX slots assigned to PE0" type="unsigned" min="0" max="2"/>
		<parameter name="SLOTS_PE1" description ="Number of TX slots assigned to PE1" type="unsigned" min="0" max="2"/>
-->
	</parameters>
	
	<system_metrics> 
	
	    <!-- Feasible metric names in KisTA -->
	  <!-- name="rtos/sched_name/plat_utilization"-->
	  <!-- name="rtos/sched_name/number_of_schedulings"-->
	  <!-- name="rtos/sched_name/starvation" -->
	  <!-- name="rtos/sched_name/miss_deadlines"-->
	  <!-- name="rtos/sched_name/sched_utilization"-->
	  <!-- name="task/task_name/utilization"-->
	  <!-- name="task/task_name/miss_deadline" -->
	  

	  
	  <!-- metrics for an environment channel -->
	  <!-- normalized  -->

		<!-- throughput reported in GHz, because A-DSE is reporting throughput in GHz too, because workloads are provided in ns to the tool -->

	  <system_metric name="rtos/sched1/tasks_utilization" type="float" />
	  <system_metric name="rtos/sched2/tasks_utilization" type="float" />
	  <system_metric name="rtos/sched3/tasks_utilization" type="float" />

	  <!-- other metrics (as an example of some supported metrics) -->
	  
	  <!-- non-normalized  thorughput
	  <system_metric name="comm_synch/E19/write_throughput" type="short" unit="bps" />
	  <system_metric name="comm_synch/E19/write_stationary_throughput" type="short" unit="bps" />
	   -->
	   
	  <!-- metrics for an internal channel -->
	  <!-- normalized 
	  <system_metric name="comm_synch/E1/normalized_write_throughput" type="voidp" unit="Hz" />
	  <system_metric name="comm_synch/E1/normalized_write_stationary_throughput" type="voidp" unit="Hz" />	  
      -->
      
	  <!-- non-normalized
	  <system_metric name="comm_synch/E1/write_throughput" type="voidp" unit="bps" />
	  <system_metric name="comm_synch/E1/write_stationary_throughput" type="voidp" unit="bps" />	  
       -->

	  <!-- some other metrics hanging from each RTOS
	  <system_metric name="rtos/sched1/sched_utilization" type="float" />
  	  <system_metric name="rtos/sched2/plat_utilization" type="float" />
  	     -->
  	     
<!-- TBS
  	  <system_metric name="PE1/mem usage" type="unsigned" unit="byte" />
  	  <system_metric name="PE2/mem usage" type="unsigned" unit="byte" />
	  <system_metric name="throughput" type="float" unit="bps" />
 -->	  
	</system_metrics>
	
	<!-- This section should comprise those input given to the A-DSE tool which are actually constraints -->
	
	<rules>

		<!-- rules for T MAPs (TBD) --> 


		<!-- A-DSE input: MAX_PE_NODES constraint -->
		<!-- Rules on the number of processing elements, given the MAX_PE_NODES constraint -->
<!--		
		<rule name="Maximum and minimum Number of Nodes">
		<and>
			<less-equal>
				<parameter name="PE_NODES"/>
				<parameter name="2"/>
			</less-equal>
			<greater-equal>
				<parameter name="PE_NODES"/>
				<parameter name="1"/>
			</greater-equal>
		</and>				
		</rule>
-->

	</rules>
	
	
</design_space>
